[
    {
        "hospital_id": "5641056",
        "patient_name": "Edward Slater",
        "patient_mrn": "cea8412e-c367-11ec-ab49-3af9d3a61d88",
        "patient_status": 2
    },
    {
        "hospital_id": "2341041",
        "patient_name": "Violette Ryan",
        "patient_mrn": "cea84156-c367-11ec-ab49-3af9d3a61d88",
        "patient_status": 1
    },
    {
        "hospital_id": "1042539",
        "patient_name": "James Benson",
        "patient_mrn": "cea84174-c367-11ec-ab49-3af9d3a61d88",
        "patient_status": 2
    },
    {
        "hospital_id": "102640475",
        "patient_name": "Alyssa Renteria",
        "patient_mrn": "cea84192-c367-11ec-ab49-3af9d3a61d88",
        "patient_status": 1
    },
    {
        "hospital_id": "6940241",
        "patient_name": "Anthony Castillo",
        "patient_mrn": "cea841b0-c367-11ec-ab49-3af9d3a61d88",
        "patient_status": 3
    },
    {
        "hospital_id": "10141075",
        "patient_name": "Tracy Mcchriston",
        "patient_mrn": "cea8420a-c367-11ec-ab49-3af9d3a61d88",
        "patient_status": 3
    },
    {
        "hospital_id": "2240004",
        "patient_name": "John Ferrell",
        "patient_mrn": "cea84264-c367-11ec-ab49-3af9d3a61d88",
        "patient_status": 2
    },
    {
        "hospital_id": "6040965",
        "patient_name": "Patrick Meese",
        "patient_mrn": "cea84282-c367-11ec-ab49-3af9d3a61d88",
        "patient_status": 1
    },
    {
        "hospital_id": "6840217",
        "patient_name": "Shirley Atkinson",
        "patient_mrn": "cea84340-c367-11ec-ab49-3af9d3a61d88",
        "patient_status": 1
    },
    {
        "hospital_id": "8640456",
        "patient_name": "Stacy Santos",
        "patient_mrn": "cea8439a-c367-11ec-ab49-3af9d3a61d88",
        "patient_status": 1
    },
    {
        "hospital_id": "9140504",
        "patient_name": "Harriet Kelley",
        "patient_mrn": "cea843d6-c367-11ec-ab49-3af9d3a61d88",
        "patient_status": 1
    },
    {
        "hospital_id": "5042276",
        "patient_name": "Robert Rankin",
        "patient_mrn": "cea84412-c367-11ec-ab49-3af9d3a61d88",
        "patient_status": 1
    },
    {
        "hospital_id": "2840324",
        "patient_name": "Jennifer Shellenbarger",
        "patient_mrn": "cea84430-c367-11ec-ab49-3af9d3a61d88",
        "patient_status": 2
    },
    {
        "hospital_id": "11342211",
        "patient_name": "Robert Myers",
        "patient_mrn": "cea844ee-c367-11ec-ab49-3af9d3a61d88",
        "patient_status": 2
    },
    {
        "hospital_id": "9941017",
        "patient_name": "Jason Skiba",
        "patient_mrn": "cea8450c-c367-11ec-ab49-3af9d3a61d88",
        "patient_status": 2
    },
    {
        "hospital_id": "7941240",
        "patient_name": "Valeri Barber",
        "patient_mrn": "cea84566-c367-11ec-ab49-3af9d3a61d88",
        "patient_status": 3
    },
    {
        "hospital_id": "12241858",
        "patient_name": "John Strange",
        "patient_mrn": "cea84584-c367-11ec-ab49-3af9d3a61d88",
        "patient_status": 3
    },
    {
        "hospital_id": "102640475",
        "patient_name": "Bertie Mcgibney",
        "patient_mrn": "cea845a2-c367-11ec-ab49-3af9d3a61d88",
        "patient_status": 2
    },
    {
        "hospital_id": "3140831",
        "patient_name": "Francis Boucher",
        "patient_mrn": "cea845c0-c367-11ec-ab49-3af9d3a61d88",
        "patient_status": 3
    },
    {
        "hospital_id": "10542718",
        "patient_name": "Jeremy Garcia",
        "patient_mrn": "cea845fc-c367-11ec-ab49-3af9d3a61d88",
        "patient_status": 2
    },
    {
        "hospital_id": "3341701",
        "patient_name": "Betty Homer",
        "patient_mrn": "cea84624-c367-11ec-ab49-3af9d3a61d88",
        "patient_status": 1
    },
    {
        "hospital_id": "10542718",
        "patient_name": "Robert Nixon",
        "patient_mrn": "cea84642-c367-11ec-ab49-3af9d3a61d88",
        "patient_status": 3
    },
    {
        "hospital_id": "9941017",
        "patient_name": "Steven Drury",
        "patient_mrn": "cea8467e-c367-11ec-ab49-3af9d3a61d88",
        "patient_status": 1
    }
]